torchadv/__init__.py
torchadv/attack.py
torchadv/attacks/__init__.py
torchadv/attacks/fgsm.py
torchadv/attacks/pgd.py
torchadv/utils/__init__.py
torchadv/utils/utils.py
torchadv-0.0.1.dist-info/LICENSE
torchadv-0.0.1.dist-info/METADATA
torchadv-0.0.1.dist-info/WHEEL
torchadv-0.0.1.dist-info/RECORD
