Metadata-Version: 2.1
Name: torchadv
Version: 0.0.1
Summary: Tiny package designed to support red teams and penetration testers in creating and analyzing adversarial attacks on PyTorch models.
Home-page: https://github.com/hupe1980/torchadv
License: MIT
Keywords: security,ai,pentest,red-team,responsible-ai,red-team-tools,ai-red-team,adversarial-attacks,pytorch,deep-learning
Author: hupe1980
Requires-Python: >=3.12,<4.0
Classifier: License :: OSI Approved :: MIT License
Classifier: Programming Language :: Python
Classifier: Programming Language :: Python :: 3
Classifier: Programming Language :: Python :: 3.12
Classifier: Topic :: Scientific/Engineering :: Artificial Intelligence
Classifier: Topic :: Security
Requires-Dist: matplotlib (>=3.9.0,<4.0.0)
Requires-Dist: numpy (>=2.0.0,<3.0.0)
Requires-Dist: torch (>=2.3.1,<3.0.0)
Project-URL: Repository, https://github.com/hupe1980/torchadv
